LICENSE
setup.py
RenePy/Utiles.py
RenePy/__init__.py
RenePy/ClasesUtiles/Compilador.py
RenePy/ClasesUtiles/Date.py
RenePy/ClasesUtiles/File.py
RenePy/ClasesUtiles/__init__.py
RenePy/ClasesUtiles/BasesDeDatos/BDArchivo.py
RenePy/ClasesUtiles/BasesDeDatos/BDConexion.py
RenePy/ClasesUtiles/BasesDeDatos/BDImagen.py
RenePy/ClasesUtiles/BasesDeDatos/BDSesionStorage.py
RenePy/ClasesUtiles/BasesDeDatos/BDUpdates.py
RenePy/ClasesUtiles/BasesDeDatos/BasicoBD.py
RenePy/ClasesUtiles/BasesDeDatos/ModeloDeApiBD.py
RenePy/ClasesUtiles/BasesDeDatos/TemporalStorage.py
RenePy/ClasesUtiles/BasesDeDatos/__init__.py
RenePy/ClasesUtiles/BasesDeDatos/Factory/ColumnaDeModeloBD.py
RenePy/ClasesUtiles/BasesDeDatos/Factory/ModeloBD.py
RenePy/ClasesUtiles/BasesDeDatos/Factory/__init__.py
RenePy/ClasesUtiles/Interfaces/Utilizar.py
RenePy/ClasesUtiles/Interfaces/__init__.py
RenePy/ClasesUtiles/Tipos/TipoDeClasificacionSQL.py
RenePy/ClasesUtiles/Tipos/TipoDeConexion.py
RenePy/ClasesUtiles/Tipos/TipoDeDatoSQL.py
RenePy/ClasesUtiles/Tipos/TipoDeImagen.py
RenePy/ClasesUtiles/Tipos/TipoDeOrdenamientoSQL.py
RenePy/ClasesUtiles/Tipos/__init__.py
RenePy/MetodosUtiles/Archivo.py
RenePy/MetodosUtiles/BD_Postgres.py
RenePy/MetodosUtiles/BD_SQLite.py
RenePy/MetodosUtiles/ConsolaUtiles.py
RenePy/MetodosUtiles/Criptomodenas.py
RenePy/MetodosUtiles/Maths.py
RenePy/MetodosUtiles/MetodosUtiles.py
RenePy/MetodosUtiles/RandomUtiles.py
RenePy/MetodosUtiles/SQL.py
RenePy/MetodosUtiles/Subprocesos.py
RenePy/MetodosUtiles/UtilesImg.py
RenePy/MetodosUtiles/__init__.py
RenePy/MetodosUtiles/Imports/BD_SQLiteImports.py
RenePy/MetodosUtiles/Imports/MetodosUtilesBasicos.py
RenePy/MetodosUtiles/Imports/SQLImports.py
RenePy/MetodosUtiles/Imports/__init__.py
RenePython.egg-info/PKG-INFO
RenePython.egg-info/SOURCES.txt
RenePython.egg-info/dependency_links.txt
RenePython.egg-info/top_level.txt